README.md
setup.py
duke_time_record_test/__init__.py
duke_time_record_test/__main__.py
duke_time_record_test/decorators.py
duke_time_record_test.egg-info/PKG-INFO
duke_time_record_test.egg-info/SOURCES.txt
duke_time_record_test.egg-info/dependency_links.txt
duke_time_record_test.egg-info/top_level.txt